jupyterlab_kernel_terminal_workspace_culler_extension/__init__.py
jupyterlab_kernel_terminal_workspace_culler_extension/_version.py
jupyterlab_kernel_terminal_workspace_culler_extension/cli.py
jupyterlab_kernel_terminal_workspace_culler_extension/culler.py
jupyterlab_kernel_terminal_workspace_culler_extension/routes.py
jupyterlab_kernel_terminal_workspace_culler_extension/tests/__init__.py
jupyterlab_kernel_terminal_workspace_culler_extension/tests/test_culler.py
jupyterlab_kernel_terminal_workspace_culler_extension/tests/test_routes.py
jupyterlab_kernel_terminal_workspace_culler_extension-1.0.21.data/data/etc/jupyter/jupyter_server_config.d/jupyterlab_kernel_terminal_workspace_culler_extension.json
jupyterlab_kernel_terminal_workspace_culler_extension-1.0.21.data/data/share/jupyter/labextensions/jupyterlab_kernel_terminal_workspace_culler_extension/package.json
jupyterlab_kernel_terminal_workspace_culler_extension-1.0.21.data/data/share/jupyter/labextensions/jupyterlab_kernel_terminal_workspace_culler_extension/schemas/jupyterlab_kernel_terminal_workspace_culler_extension/package.json.orig
jupyterlab_kernel_terminal_workspace_culler_extension-1.0.21.data/data/share/jupyter/labextensions/jupyterlab_kernel_terminal_workspace_culler_extension/schemas/jupyterlab_kernel_terminal_workspace_culler_extension/plugin.json
jupyterlab_kernel_terminal_workspace_culler_extension-1.0.21.data/data/share/jupyter/labextensions/jupyterlab_kernel_terminal_workspace_culler_extension/static/728.b056947597422f9e496c.js
jupyterlab_kernel_terminal_workspace_culler_extension-1.0.21.data/data/share/jupyter/labextensions/jupyterlab_kernel_terminal_workspace_culler_extension/static/750.b2aa372edac477cffcb9.js
jupyterlab_kernel_terminal_workspace_culler_extension-1.0.21.data/data/share/jupyter/labextensions/jupyterlab_kernel_terminal_workspace_culler_extension/static/remoteEntry.61977aac2cfde9b88947.js
jupyterlab_kernel_terminal_workspace_culler_extension-1.0.21.dist-info/METADATA
jupyterlab_kernel_terminal_workspace_culler_extension-1.0.21.dist-info/WHEEL
jupyterlab_kernel_terminal_workspace_culler_extension-1.0.21.dist-info/entry_points.txt
jupyterlab_kernel_terminal_workspace_culler_extension-1.0.21.dist-info/licenses/LICENSE
jupyterlab_kernel_terminal_workspace_culler_extension-1.0.21.dist-info/RECORD
