Metadata-Version: 2.4
Name: jupyterlab_kernel_terminal_workspace_culler_extension
Version: 1.0.21
Summary: Jupyterlab extension to kill unused kernels, terminals and workspaces. User can configure the idle time (minutes) after which the resource will be released automatically. This helps with the locked memory, insane number of terminals opened etc.
Project-URL: Homepage, https://github.com/stellarshenson/jupyterlab_kernel_terminal_workspace_culler_extension
Project-URL: Bug Tracker, https://github.com/stellarshenson/jupyterlab_kernel_terminal_workspace_culler_extension/issues
Project-URL: Repository, https://github.com/stellarshenson/jupyterlab_kernel_terminal_workspace_culler_extension.git
Author-email: Stellars Henson <konrad.jelen@gmail.com>
License: BSD 3-Clause License
License-File: LICENSE
Keywords: jupyter,jupyterlab,jupyterlab-extension
Classifier: Framework :: Jupyter
Classifier: Framework :: Jupyter :: JupyterLab
Classifier: Framework :: Jupyter :: JupyterLab :: 4
Classifier: Framework :: Jupyter :: JupyterLab :: Extensions
Classifier: Framework :: Jupyter :: JupyterLab :: Extensions :: Prebuilt
Classifier: License :: OSI Approved :: BSD License
Classifier: Programming Language :: Python
Classifier: Programming Language :: Python :: 3
Classifier: Programming Language :: Python :: 3.10
Classifier: Programming Language :: Python :: 3.11
Classifier: Programming Language :: Python :: 3.12
Classifier: Programming Language :: Python :: 3.13
Classifier: Programming Language :: Python :: 3.14
Requires-Python: >=3.10
Requires-Dist: jupyter-server<3,>=2.4.0
Requires-Dist: requests>=2.20.0
Provides-Extra: dev
Requires-Dist: jupyterlab>=4; extra == 'dev'
Provides-Extra: notifications
Requires-Dist: jupyterlab-notifications-extension; extra == 'notifications'
Provides-Extra: test
Requires-Dist: coverage; extra == 'test'
Requires-Dist: pytest; extra == 'test'
Requires-Dist: pytest-asyncio; extra == 'test'
Requires-Dist: pytest-cov; extra == 'test'
Requires-Dist: pytest-jupyter[server]>=0.6.0; extra == 'test'
